kube_debugger/__init__.py
kube_debugger/main.py
kube_debugger/pod/__init__.py
kube_debugger/pod/config_error.py
kube_debugger/pod/crash_loop_backoff.py
kube_debugger/pod/detect_exit_code.py
kube_debugger/pod/image_pull_backoff.py
kube_debugger/pod/pod_utils.py
kube_debugger/utils/__init__.py
kube_debugger/utils/ai_init.py
kube_debugger/utils/config.py
kube_debugger/utils/logger.py
kube_debugger-0.0.5.dist-info/METADATA
kube_debugger-0.0.5.dist-info/WHEEL
kube_debugger-0.0.5.dist-info/entry_points.txt
kube_debugger-0.0.5.dist-info/top_level.txt
kube_debugger-0.0.5.dist-info/RECORD
