Metadata-Version: 2.1
Name: kube-debugger
Version: 0.0.5
Summary: Kube-Debugger is a Kubernetes CLI Tool which will help you debug your cluster
Home-page: https://github.com/Ayushmishra05/KubeDebugger
Author: Ayush Mishra A
Author-email: ayush89718@gmail.com
License: MIT
Classifier: Development Status :: 3 - Alpha
Classifier: Intended Audience :: Developers
Classifier: Programming Language :: Python :: 3
Classifier: License :: OSI Approved :: MIT License
Classifier: Operating System :: OS Independent
Requires-Python: >=3.10
Requires-Dist: langchain-core ==0.3.72
Requires-Dist: langchain-groq ==0.3.6
Requires-Dist: python-dotenv ==1.1.1
Requires-Dist: PyYAML ==6.0.1
Requires-Dist: Requests ==2.32.4
Requires-Dist: setuptools ==69.5.1
Requires-Dist: typer ==0.16.0
